vtu_aiml/Prog1.py
vtu_aiml/Prog2.py
vtu_aiml/Prog3.py
vtu_aiml/Prog4.py
vtu_aiml/Prog5.py
vtu_aiml/Prog6.py
vtu_aiml/Prog7.py
vtu_aiml/Prog8.py
vtu_aiml/Prog9.py
vtu_aiml/__init__.py
vtu_aiml/get_dataset.py
vtu_aiml/get_program.py
vtu_aiml-0.1.2.dist-info/LICENSE
vtu_aiml-0.1.2.dist-info/METADATA
vtu_aiml-0.1.2.dist-info/WHEEL
vtu_aiml-0.1.2.dist-info/top_level.txt
vtu_aiml-0.1.2.dist-info/RECORD
