Metadata-Version: 2.1
Name: vtu-aiml
Version: 0.1.2
Summary: A example Python package
Home-page: https://github.com/shuds13/pyexample
Author: Hrithikesh
Author-email: hrithikesh@gmail.com
License: BSD 2-clause
Platform: UNKNOWN
License-File: LICENSE
